MANIFEST.in
requirements.txt
setup.cfg
setup.py
pyPluribus/__init__.py
pyPluribus/config.py
pyPluribus/device.py
pyPluribus/exceptions.py
pyPluribus.egg-info/PKG-INFO
pyPluribus.egg-info/SOURCES.txt
pyPluribus.egg-info/dependency_links.txt
pyPluribus.egg-info/requires.txt
pyPluribus.egg-info/top_level.txt