Metadata-Version: 1.1
Name: pyPluribus
Version: 0.3.1
Summary: Python API to interact with Pluribus devices
Home-page: https://github.com/mirceaulinic/pypluribus
Author: Mircea Ulinic
Author-email: mirucha@cloudflare.com
License: Apache 2.0
Download-URL: https://github.com/mirceaulinic/pypluribus/tarball/0.3.1
Keywords: Pluribus,networking
Platform: any
Classifier: Development Status :: 5 - Production/Stable
Classifier: Intended Audience :: Developers
Classifier: Intended Audience :: Science/Research
Classifier: Intended Audience :: System Administrators
Classifier: Intended Audience :: Telecommunications Industry
Classifier: License :: OSI Approved :: Apache Software License
Classifier: Operating System :: OS Independent
Classifier: Topic :: System :: Networking
Classifier: Topic :: Utilities
Classifier: Topic :: Software Development :: Libraries
Classifier: Topic :: Software Development :: Libraries :: Python Modules
Classifier: Topic :: Software Development :: Libraries :: Application Frameworks
Classifier: Topic :: Scientific/Engineering
Classifier: Programming Language :: Python :: 2.6
Classifier: Programming Language :: Python :: 2.7
Classifier: Programming Language :: Python :: 3.4
Classifier: Programming Language :: Python :: 3.5
